<?xml version="1.0" encoding="utf-8"?>
<Defs>
<AlienRace.ThingDef_AlienRace ParentName="BaseSquish">
    <defName>BasicPanda</defName>
    <label>Panda Squishable</label>
    
		<description>Pandas: Majestic! Graceful! Fierce! Lords of all they surv...no, wait, I'm thinking about dragons. Pandas are actually the opposite of all that. Pandas are the ones that like to snuggle down in a tasty patch of bamboo for 23 hours a day. The ones that want nothing more than a nice branch to sit on and a good book to read. The ones that are so happy and chill that they can't even be bothered to reproduce. Pandas! Cuddly, wiggly fuzzy pandas! This new "extra happy" version of our classic Squishable Panda is even MORE relaxed about the world. It also breathes fire! No wait, that's dragons again.</description>
        
    <statBases>
      <ComfyTemperatureMin>-15</ComfyTemperatureMin>
      <ComfyTemperatureMax>28</ComfyTemperatureMax>
      <LeatherAmount>0</LeatherAmount>
      <MarketValue>2500</MarketValue>
      <Flammability>2.0</Flammability>
      <SocialImpact>0.2</SocialImpact>
    </statBases>

    <tools>
      <li>
        <label>left paw</label>
        <capacities>
          <li>Blunt</li>
        </capacities>
        <power>7</power>
        <cooldownTime>2</cooldownTime>
        <linkedBodyPartsGroup>LeftHand</linkedBodyPartsGroup>
      </li>
      <li>
        <label>right paw</label>
        <capacities>
          <li>Blunt</li>
        </capacities>
        <power>7</power>
        <cooldownTime>2</cooldownTime>
        <linkedBodyPartsGroup>RightHand</linkedBodyPartsGroup>
      </li>
      <li>
        <label>teeth</label>
        <capacities>
          <li>Bite</li>
        </capacities>
        <power>8</power>
        <cooldownTime>6</cooldownTime>
        <linkedBodyPartsGroup>Teeth</linkedBodyPartsGroup>
        <chanceFactor>0.5</chanceFactor>	
      </li>
      <li>
        <label>head</label>
        <capacities>
          <li>Blunt</li>
        </capacities>
        <power>3</power>
        <cooldownTime>6</cooldownTime>
        <linkedBodyPartsGroup>HeadAttackTool</linkedBodyPartsGroup>
        <ensureLinkedBodyPartsGroupAlwaysUsable>true</ensureLinkedBodyPartsGroupAlwaysUsable>
        <chanceFactor>0.2</chanceFactor>
        <surpriseAttack>
          <extraMeleeDamages>
            <li>
              <def>Stun</def>
              <amount>6</amount>
            </li>
          </extraMeleeDamages>
        </surpriseAttack>			
      </li>
    </tools>
	
    <alienRace>
	
        <generalSettings>
		
	  <forcedRaceTraitEntries>
		<li>
			<defName>Industriousness</defName>
			<chance>10</chance>
			<degree>-1</degree>
		</li>
		<li>
			<defName>Industriousness</defName>
			<chance>10</chance>
			<degree>-2</degree>
		</li>
	  </forcedRaceTraitEntries>		
		

			<alienPartGenerator>
		    
			<alienbodytypes>
                <li>Fat</li>
            </alienbodytypes>
			
			</alienPartGenerator>	          

		</generalSettings>
        
		<graphicPaths>
            <li>
                <body>Squish/Panda/</body>
                <head>Squish/Head/</head>
                <skeleton></skeleton>
                <skull></skull>
            </li>
        </graphicPaths>

        <hairSettings>
			<hasHair>false</hasHair>
        </hairSettings>



        <thoughtSettings>
            <replacerList>
                <li>
                    <original>KnowColonistDied</original>
                    <replacer>KnowColonistDiedSquish</replacer>
			    </li>
				<li>
                    <original>BondedAnimalDied</original>
                    <replacer>BondedAnimalDiedSquish</replacer>
			    </li>
				<li>    
					<original>PawnWithGoodOpinionDied</original>
                    <replacer>PawnWithGoodOpinionDiedSquish</replacer>
			    </li>
				<li>
    				<original>MySonDied</original>
                    <replacer>MySonDiedSquish</replacer>
			    </li>
				<li>    
					<original>MyDaughterDied</original>
                    <replacer>MyDaughterDiedSquish</replacer>
			    </li>
				<li>                
		    		<original>MyHusbandDied</original>
                    <replacer>MyHusbandDiedSquish</replacer>
			    </li>
				<li>            
        			<original>MyWifeDied</original>
                    <replacer>MyWifeDiedSquish</replacer>
			    </li>
				<li>                    
					<original>MyFianceDied</original>
                    <replacer>MyFianceDiedSquish</replacer>
			    </li>
				<li>                    
					<original>MyFianceeDied</original>
                    <replacer>MyFianceeDiedSquish</replacer>
			    </li>
				<li>                    
					<original>MyLoverDied</original>
                    <replacer>MyLoverDiedSquish</replacer>
			    </li>
				<li>                    
					<original>MyBrotherDied</original>
                    <replacer>MyBrotherDiedSquish</replacer>
			    </li>
				<li>                    
					<original>MySisterDied</original>
                    <replacer>MySisterDiedSquish</replacer>
			    </li>
				<li>                    
					<original>MyGrandchildDied</original>
                    <replacer>MyGrandchildDiedSquish</replacer>
			    </li>
				<li>                    
					<original>MyFatherDied</original>
                    <replacer>MyFatherDiedSquish</replacer>
			    </li>
				<li>                    
					<original>MyMotherDied</original>
                    <replacer>MyMotherDiedSquish</replacer>
			    </li>
				<li>                    
					<original>MyNieceDied</original>
                    <replacer>MyNieceDiedSquish</replacer>
			    </li>
				<li>                    
					<original>MyNephewDied</original>
                    <replacer>MyNephewDiedSquish</replacer>
			    </li>
				<li>                    
					<original>MyHalfSiblingDied</original>
                    <replacer>MyHalfSiblingDiedSquish</replacer>
			    </li>
				<li>                    
					<original>MyAuntDied</original>
                    <replacer>MyAuntDiedSquish</replacer>
			    </li>
				<li>                    
					<original>MyUncleDied</original>
                    <replacer>MyUncleDiedSquish</replacer>
			    </li>
				<li>                    
					<original>MyGrandparentDied</original>
                    <replacer>MyGrandparentDiedSquish</replacer>
			    </li>
				<li>                    
					<original>MyCousinDied</original>
                    <replacer>MyCousinDiedSquish</replacer>
			    </li>
				<li>                    
					<original>MyKinDied</original>
                    <replacer>MyKinDiedSquish</replacer>
                </li>
            </replacerList>
			
            <cannotReceiveThoughts>
                <li>AteKibble</li>
                <li>AteHumanlikeMeatDirect</li>
                <li>AteHumanlikeMeatDirectCannibal</li>
                <li>AteHumanlikeMeatAsIngredient</li>
                <li>AteHumanlikeMeatAsIngredientCannibal</li>
                <li>AteInsectMeatDirect</li>
                <li>AteInsectMeatAsIngredient</li>
				<li>Naked</li>
            </cannotReceiveThoughts>		
        </thoughtSettings>
		
  
    </alienRace>
    
<race>

      <thinkTreeMain>Humanlike</thinkTreeMain>
      <thinkTreeConstant>HumanlikeConstant</thinkTreeConstant>
      <intelligence>Humanlike</intelligence>
      <makesFootprints>true</makesFootprints>
      <lifeExpectancy>70</lifeExpectancy>
      <bloodDef></bloodDef>
	  <leatherDef>Leather_Patch</leatherDef>


      <baseBodySize>1.0</baseBodySize>
      <baseHungerRate>1.0</baseHungerRate>
      <foodType>VegetarianRoughAnimal</foodType>
      <gestationPeriodDays>45</gestationPeriodDays>
      <litterSizeCurve>
        <points>
          <li>(0.5, 0)</li>
          <li>(1, 1)</li>
          <li>(1.01, 0.02)</li>
          <li>(3.5, 0)</li>
        </points>
      </litterSizeCurve>
      <lifeStageAges>
        <li>
          <def>HumanlikeBaby</def>
          <minAge>0</minAge>
        </li>
        <li>
          <def>HumanlikeToddler</def>
          <minAge>2</minAge>
        </li>
        <li>
          <def>HumanlikeChild</def>
          <minAge>4</minAge>
        </li>
        <li>
          <def>HumanlikeTeenager</def>
          <minAge>13</minAge>
        </li>
        <li>
          <def>HumanlikeAdult</def>
          <minAge>18</minAge>
        </li>
      </lifeStageAges>
      <soundMeleeHitPawn>Pawn_Melee_Punch_HitPawn</soundMeleeHitPawn>
      <soundMeleeHitBuilding>Pawn_Melee_Punch_HitBuilding</soundMeleeHitBuilding>
      <soundMeleeMiss>Pawn_Melee_Punch_Miss</soundMeleeMiss>
      <ageGenerationCurve>
        <points>
          <li>(14,0)</li>
          <li>(16,100)</li>
          <li>(50,100)</li>
          <li>(60,30)</li>
          <li>(70,18)</li>
          <li>(80,10)</li>
          <li>(90,3)</li>
          <li>(100,0)</li>
        </points>
      </ageGenerationCurve>


</race>	

    
</AlienRace.ThingDef_AlienRace>
</Defs>